depmanager/__init__.py
depmanager/manager.py
depmanager/api/__init__.py
depmanager/api/builder.py
depmanager/api/load.py
depmanager/api/local.py
depmanager/api/package.py
depmanager/api/recipe.py
depmanager/api/remotes.py
depmanager/api/toolsets.py
depmanager/api/internal/__init__.py
depmanager/api/internal/common.py
depmanager/api/internal/config_file.py
depmanager/api/internal/crypto.py
depmanager/api/internal/data_locking.py
depmanager/api/internal/database_common.py
depmanager/api/internal/database_local.py
depmanager/api/internal/database_remote_folder.py
depmanager/api/internal/database_remote_ftp.py
depmanager/api/internal/database_remote_server.py
depmanager/api/internal/dependency.py
depmanager/api/internal/machine.py
depmanager/api/internal/messaging.py
depmanager/api/internal/recipe_builder.py
depmanager/api/internal/system.py
depmanager/api/internal/toolset.py
depmanager/cmake/DepManager.cmake
depmanager/command/__init__.py
depmanager/command/build.py
depmanager/command/get.py
depmanager/command/info.py
depmanager/command/load.py
depmanager/command/pack.py
depmanager/command/remote.py
depmanager/command/toolset.py
depmanager-0.5.2.dist-info/licenses/LICENSE
depmanager-0.5.2.dist-info/METADATA
depmanager-0.5.2.dist-info/WHEEL
depmanager-0.5.2.dist-info/entry_points.txt
depmanager-0.5.2.dist-info/top_level.txt
depmanager-0.5.2.dist-info/RECORD
