Metadata-Version: 2.4
Name: depmanager
Version: 0.5.2
Summary: Simple Dependency manager
Author-email: Silmaen <genteur.slayer@laposte.net>
Project-URL: Homepage, https://github.com/Silmaen/DepManager
Keywords: dependency,development,cmake,C++
Classifier: Development Status :: 4 - Beta
Classifier: Intended Audience :: Developers
Classifier: Topic :: Software Development :: Build Tools
Classifier: Programming Language :: Python :: 3
Requires-Python: >=3.9
License-File: LICENSE
Requires-Dist: requests
Requires-Dist: requests-toolbelt
Requires-Dist: PyYAML
Requires-Dist: rich
Requires-Dist: cryptography
Dynamic: license-file
